atex/__init__.py
atex/fmf.py
atex/aggregator/__init__.py
atex/aggregator/json.py
atex/cli/__init__.py
atex/cli/fmf.py
atex/cli/libvirt.py
atex/cli/testingfarm.py
atex/connection/__init__.py
atex/connection/podman.py
atex/connection/ssh.py
atex/executor/__init__.py
atex/executor/duration.py
atex/executor/executor.py
atex/executor/reporter.py
atex/executor/scripts.py
atex/executor/testcontrol.py
atex/orchestrator/__init__.py
atex/orchestrator/adhoc.py
atex/orchestrator/contest.py
atex/provisioner/__init__.py
atex/provisioner/libvirt/VM_PROVISION
atex/provisioner/libvirt/__init__.py
atex/provisioner/libvirt/libvirt.py
atex/provisioner/libvirt/locking.py
atex/provisioner/libvirt/setup-libvirt.sh
atex/provisioner/podman/__init__.py
atex/provisioner/podman/podman.py
atex/provisioner/testingfarm/__init__.py
atex/provisioner/testingfarm/api.py
atex/provisioner/testingfarm/testingfarm.py
atex/util/__init__.py
atex/util/dedent.py
atex/util/libvirt.py
atex/util/log.py
atex/util/named_mapping.py
atex/util/path.py
atex/util/ssh_keygen.py
atex/util/subprocess.py
atex/util/threads.py
atex-0.11.dist-info/METADATA
atex-0.11.dist-info/WHEEL
atex-0.11.dist-info/entry_points.txt
atex-0.11.dist-info/licenses/COPYING.txt
atex-0.11.dist-info/RECORD
