Metadata-Version: 2.4
Name: atex
Version: 0.11
Summary: Ad-hoc Test EXecutor
Project-URL: Homepage, https://github.com/RHSecurityCompliance/atex
License-Expression: GPL-3.0-or-later
License-File: COPYING.txt
Classifier: Operating System :: POSIX :: Linux
Classifier: Programming Language :: Python :: 3
Classifier: Topic :: Software Development :: Testing
Requires-Python: >=3.11
Requires-Dist: fmf>=1.6
Requires-Dist: pyyaml
Requires-Dist: urllib3<3,>=2
